mdtraj/__init__.py
mdtraj/_lprmsd.cpython-313-x86_64-linux-gnu.so
mdtraj/_rmsd.cpython-313-x86_64-linux-gnu.so
mdtraj/_version.py
mdtraj/io.py
mdtraj/core/__init__.py
mdtraj/core/element.py
mdtraj/core/residue_names.py
mdtraj/core/selection.py
mdtraj/core/topology.py
mdtraj/core/trajectory.py
mdtraj/core/lib/center.h
mdtraj/core/lib/libtheobald.a
mdtraj/core/lib/theobald_rmsd.h
mdtraj/formats/__init__.py
mdtraj/formats/amberrst.py
mdtraj/formats/arc.py
mdtraj/formats/dcd.cpython-313-x86_64-linux-gnu.so
mdtraj/formats/dtr.cpython-313-x86_64-linux-gnu.so
mdtraj/formats/gro.py
mdtraj/formats/gsd.py
mdtraj/formats/hdf5.py
mdtraj/formats/hoomdxml.py
mdtraj/formats/lammpstrj.py
mdtraj/formats/lh5.py
mdtraj/formats/mdcrd.py
mdtraj/formats/mol2.py
mdtraj/formats/netcdf.py
mdtraj/formats/openmmxml.py
mdtraj/formats/prmtop.py
mdtraj/formats/psf.py
mdtraj/formats/registry.py
mdtraj/formats/trr.cpython-313-x86_64-linux-gnu.so
mdtraj/formats/xtc.cpython-313-x86_64-linux-gnu.so
mdtraj/formats/xyzfile.py
mdtraj/formats/pdb/__init__.py
mdtraj/formats/pdb/pdbfile.py
mdtraj/formats/pdb/pdbstructure.py
mdtraj/formats/pdb/data/pdbNames.xml
mdtraj/formats/pdb/data/residues.xml
mdtraj/formats/pdbx/PdbxContainers.py
mdtraj/formats/pdbx/PdbxReader.py
mdtraj/formats/pdbx/__init__.py
mdtraj/formats/pdbx/pdbx.py
mdtraj/formats/pdbx/pdbxfile.py
mdtraj/geometry/__init__.py
mdtraj/geometry/_geometry.cpython-313-x86_64-linux-gnu.so
mdtraj/geometry/alignment.py
mdtraj/geometry/angle.py
mdtraj/geometry/contact.py
mdtraj/geometry/dihedral.py
mdtraj/geometry/distance.py
mdtraj/geometry/drid.cpython-313-x86_64-linux-gnu.so
mdtraj/geometry/dssp.py
mdtraj/geometry/hbond.py
mdtraj/geometry/internal.py
mdtraj/geometry/neighborlist.cpython-313-x86_64-linux-gnu.so
mdtraj/geometry/neighbors.cpython-313-x86_64-linux-gnu.so
mdtraj/geometry/order.py
mdtraj/geometry/pi_stacking.py
mdtraj/geometry/rdf.py
mdtraj/geometry/rg.py
mdtraj/geometry/sasa.py
mdtraj-1.11.1.post1.dist-info/METADATA
mdtraj-1.11.1.post1.dist-info/WHEEL
mdtraj-1.11.1.post1.dist-info/entry_points.txt
mdtraj-1.11.1.post1.dist-info/top_level.txt
mdtraj-1.11.1.post1.dist-info/RECORD
mdtraj-1.11.1.post1.dist-info/licenses/LICENSE
mdtraj-1.11.1.post1.dist-info/sboms/auditwheel.cdx.json
