Metadata-Version: 2.4
Name: mdtraj
Version: 1.11.1.post1
Summary: MDTraj: A modern, open library for the analysis of molecular dynamics trajectories
Home-page: http://mdtraj.org
Download-URL: https://github.com/rmcgibbo/mdtraj/releases/latest
Author: Robert McGibbon
Author-email: rmcgibbo@gmail.com
License: LGPLv2.1+
Platform: Linux
Platform: Mac OS-X
Platform: Unix
Platform: Windows
Classifier: Development Status :: 5 - Production/Stable
Classifier: Intended Audience :: Science/Research
Classifier: Intended Audience :: Developers
Classifier: License :: OSI Approved :: GNU Lesser General Public License v2 or later (LGPLv2+)
Classifier: Programming Language :: C
Classifier: Programming Language :: Python
Classifier: Programming Language :: Python :: 3
Classifier: Topic :: Scientific/Engineering :: Bio-Informatics
Classifier: Topic :: Scientific/Engineering :: Chemistry
Classifier: Operating System :: Microsoft :: Windows
Classifier: Operating System :: POSIX
Classifier: Operating System :: Unix
Classifier: Operating System :: MacOS
Requires-Python: >=3.11
License-File: LICENSE
Requires-Dist: numpy~=2.0
Requires-Dist: scipy
Requires-Dist: pyparsing
Requires-Dist: packaging
Provides-Extra: tests
Requires-Dist: pytest; extra == "tests"
Requires-Dist: pytest-rerunfailures; extra == "tests"
Requires-Dist: pytest-xdist; extra == "tests"
Provides-Extra: optional
Requires-Dist: tables; extra == "optional"
Requires-Dist: networkx; extra == "optional"
Requires-Dist: netCDF4; extra == "optional"
Requires-Dist: pandas<3; extra == "optional"
Provides-Extra: all
Requires-Dist: pytest; extra == "all"
Requires-Dist: pytest-rerunfailures; extra == "all"
Requires-Dist: pytest-xdist; extra == "all"
Requires-Dist: tables; extra == "all"
Requires-Dist: networkx; extra == "all"
Requires-Dist: netCDF4; extra == "all"
Requires-Dist: pandas<3; extra == "all"
Dynamic: author
Dynamic: author-email
Dynamic: classifier
Dynamic: description
Dynamic: download-url
Dynamic: home-page
Dynamic: license
Dynamic: license-file
Dynamic: platform
Dynamic: provides-extra
Dynamic: requires-dist
Dynamic: requires-python
Dynamic: summary
